[
 {
  "ID": "12d397cdcd594a8d9560dea5b2865301",
  "ORDERS": 1,
  "TOP_SITE": "2",
  "CREATE_TIME": "2026-07-01 20:06:23.0",
  "IF_ISSUED": "1",
  "IF_DEL": "2",
  "CHANNEL_ID": "8a9e3a9d9e38a74b019f1d90a5fb0ee1",
  "MAIN_BODY": "<p style=\"margin: 0px; white-space: normal; text-align: center;\"><img style=\"display: block; width: 100% !important; max-width: 650px !important; height: auto !important; max-height: none !important; margin: 0 auto;\" src=\"/cmsFileManager/UeditorImg/387236e1770145e895d80c35a04c7698.jpg\"/></p>"
 }
]